[
{"type":"text", "label":"", "value":"address", "requiredBy":["Application-GF-Fields.pdf", "AffordableHousing_Application sales-Fields.pdf", "Application-PCV-Fields.pdf", "Avalon Princeton - Preliminary Application Rev-Mar-2016-Fields.pdf"]},
{"type":"text", "label":"", "value":"applicantSignature", "requiredBy":["Application-GF-Fields.pdf", "AffordableHousing_Application sales-Fields.pdf", "Application-PCV-Fields.pdf", "Avalon Princeton - Preliminary Application Rev-Mar-2016-Fields.pdf"]},
{"type":"text", "label":"", "value":"applicantSignatureDate", "requiredBy":["Application-GF-Fields.pdf", "AffordableHousing_Application sales-Fields.pdf", "Avalon Princeton - Preliminary Application Rev-Mar-2016-Fields.pdf"]},
{"type":"text", "label":"", "value":"assetAccountType1", "requiredBy":["Application-GF-Fields.pdf", "AffordableHousing_Application sales-Fields.pdf", "Avalon Princeton - Preliminary Application Rev-Mar-2016-Fields.pdf"]},
{"type":"text", "label":"", "value":"assetAccountType2", "requiredBy":["Application-GF-Fields.pdf", "AffordableHousing_Application sales-Fields.pdf", "Avalon Princeton - Preliminary Application Rev-Mar-2016-Fields.pdf"]},
{"type":"text", "label":"", "value":"assetAccountType3", "requiredBy":["Application-GF-Fields.pdf", "AffordableHousing_Application sales-Fields.pdf", "Avalon Princeton - Preliminary Application Rev-Mar-2016-Fields.pdf"]},
{"type":"text", "label":"", "value":"assetAccountType4", "requiredBy":["Application-GF-Fields.pdf", "Avalon Princeton - Preliminary Application Rev-Mar-2016-Fields.pdf"]},
{"type":"text", "label":"", "value":"assetAmount1", "requiredBy":["Application-GF-Fields.pdf", "AffordableHousing_Application sales-Fields.pdf", "Avalon Princeton - Preliminary Application Rev-Mar-2016-Fields.pdf"]},
{"type":"text", "label":"", "value":"assetAmount2", "requiredBy":["Application-GF-Fields.pdf", "AffordableHousing_Application sales-Fields.pdf", "Avalon Princeton - Preliminary Application Rev-Mar-2016-Fields.pdf"]},
{"type":"text", "label":"", "value":"assetAmount3", "requiredBy":["Application-GF-Fields.pdf", "AffordableHousing_Application sales-Fields.pdf", "Avalon Princeton - Preliminary Application Rev-Mar-2016-Fields.pdf"]},
{"type":"text", "label":"", "value":"assetAmount4", "requiredBy":["Application-GF-Fields.pdf", "Avalon Princeton - Preliminary Application Rev-Mar-2016-Fields.pdf"]},
{"type":"text", "label":"", "value":"cell", "requiredBy":["Application-GF-Fields.pdf", "AffordableHousing_Application sales-Fields.pdf", "Application-PCV-Fields.pdf", "Avalon Princeton - Preliminary Application Rev-Mar-2016-Fields.pdf"]},
{"type":"text", "label":"", "value":"city", "requiredBy":["Application-GF-Fields.pdf", "AffordableHousing_Application sales-Fields.pdf", "Application-PCV-Fields.pdf", "Avalon Princeton - Preliminary Application Rev-Mar-2016-Fields.pdf"]},
{"type":"text", "label":"", "value":"coApplicantDate", "requiredBy":["AffordableHousing_Application sales-Fields.pdf"]},
{"type":"text", "label":"", "value":"coApplicantSignature", "requiredBy":["Application-GF-Fields.pdf", "AffordableHousing_Application sales-Fields.pdf"]},
{"type":"text", "label":"", "value":"coApplicantSignature1", "requiredBy":["Application-PCV-Fields.pdf", "Avalon Princeton - Preliminary Application Rev-Mar-2016-Fields.pdf"]},
{"type":"text", "label":"", "value":"coApplicantSignature2", "requiredBy":["Application-PCV-Fields.pdf", "Avalon Princeton - Preliminary Application Rev-Mar-2016-Fields.pdf"]},
{"type":"text", "label":"", "value":"coApplicantSignatureDate", "requiredBy":["Application-GF-Fields.pdf"]},
{"type":"text", "label":"", "value":"coApplicantSignatureDate1", "requiredBy":["Avalon Princeton - Preliminary Application Rev-Mar-2016-Fields.pdf"]},
{"type":"text", "label":"", "value":"coApplicantSignatureDate2", "requiredBy":["Avalon Princeton - Preliminary Application Rev-Mar-2016-Fields.pdf"]},
{"type":"text", "label":"", "value":"creditCardName1", "requiredBy":["AffordableHousing_Application sales-Fields.pdf"]},
{"type":"text", "label":"", "value":"creditCardName2", "requiredBy":["AffordableHousing_Application sales-Fields.pdf"]},
{"type":"text", "label":"", "value":"creditCardName3", "requiredBy":["AffordableHousing_Application sales-Fields.pdf"]},
{"type":"text", "label":"", "value":"creditCardName4", "requiredBy":["AffordableHousing_Application sales-Fields.pdf"]},
{"type":"text", "label":"", "value":"driversLicenseNumber1", "requiredBy":["Application-GF-Fields.pdf", "AffordableHousing_Application sales-Fields.pdf", "Application-PCV-Fields.pdf", "Avalon Princeton - Preliminary Application Rev-Mar-2016-Fields.pdf"]},
{"type":"text", "label":"", "value":"driversLicenseNumber2", "requiredBy":["Application-GF-Fields.pdf", "AffordableHousing_Application sales-Fields.pdf", "Application-PCV-Fields.pdf", "Avalon Princeton - Preliminary Application Rev-Mar-2016-Fields.pdf"]},
{"type":"text", "label":"", "value":"driversLicenseNumber3", "requiredBy":["Application-GF-Fields.pdf", "AffordableHousing_Application sales-Fields.pdf", "Application-PCV-Fields.pdf", "Avalon Princeton - Preliminary Application Rev-Mar-2016-Fields.pdf"]},
{"type":"text", "label":"", "value":"driversLicenseState1", "requiredBy":["Application-GF-Fields.pdf", "AffordableHousing_Application sales-Fields.pdf", "Application-PCV-Fields.pdf", "Avalon Princeton - Preliminary Application Rev-Mar-2016-Fields.pdf"]},
{"type":"text", "label":"", "value":"driversLicenseState2", "requiredBy":["Application-GF-Fields.pdf", "AffordableHousing_Application sales-Fields.pdf", "Application-PCV-Fields.pdf", "Avalon Princeton - Preliminary Application Rev-Mar-2016-Fields.pdf"]},
{"type":"text", "label":"", "value":"driversLicenseState3", "requiredBy":["Application-GF-Fields.pdf", "AffordableHousing_Application sales-Fields.pdf", "Application-PCV-Fields.pdf", "Avalon Princeton - Preliminary Application Rev-Mar-2016-Fields.pdf"]},
{"type":"text", "label":"", "value":"email", "requiredBy":["Application-GF-Fields.pdf"]},
{"type":"text", "label":"", "value":"extraIncomeAmount1", "requiredBy":["Application-GF-Fields.pdf", "AffordableHousing_Application sales-Fields.pdf", "Avalon Princeton - Preliminary Application Rev-Mar-2016-Fields.pdf"]},
{"type":"text", "label":"", "value":"extraIncomeAmount2", "requiredBy":["Application-GF-Fields.pdf", "AffordableHousing_Application sales-Fields.pdf", "Avalon Princeton - Preliminary Application Rev-Mar-2016-Fields.pdf"]},
{"type":"text", "label":"", "value":"extraIncomeAmount3", "requiredBy":["Application-GF-Fields.pdf", "AffordableHousing_Application sales-Fields.pdf", "Avalon Princeton - Preliminary Application Rev-Mar-2016-Fields.pdf"]},
{"type":"text", "label":"", "value":"extraIncomeAmount4", "requiredBy":["Application-GF-Fields.pdf", "Avalon Princeton - Preliminary Application Rev-Mar-2016-Fields.pdf"]},
{"type":"text", "label":"", "value":"extraIncomeFrequency1", "requiredBy":["Application-GF-Fields.pdf", "AffordableHousing_Application sales-Fields.pdf", "Avalon Princeton - Preliminary Application Rev-Mar-2016-Fields.pdf"]},
{"type":"text", "label":"", "value":"extraIncomeFrequency2", "requiredBy":["Application-GF-Fields.pdf", "AffordableHousing_Application sales-Fields.pdf", "Avalon Princeton - Preliminary Application Rev-Mar-2016-Fields.pdf"]},
{"type":"text", "label":"", "value":"extraIncomeFrequency3", "requiredBy":["Application-GF-Fields.pdf", "AffordableHousing_Application sales-Fields.pdf", "Avalon Princeton - Preliminary Application Rev-Mar-2016-Fields.pdf"]},
{"type":"text", "label":"", "value":"extraIncomeFrequency4", "requiredBy":["Application-GF-Fields.pdf", "Avalon Princeton - Preliminary Application Rev-Mar-2016-Fields.pdf"]},
{"type":"text", "label":"", "value":"extraIncomeSource1", "requiredBy":["Application-GF-Fields.pdf", "AffordableHousing_Application sales-Fields.pdf", "Avalon Princeton - Preliminary Application Rev-Mar-2016-Fields.pdf"]},
{"type":"text", "label":"", "value":"extraIncomeSource2", "requiredBy":["Application-GF-Fields.pdf", "AffordableHousing_Application sales-Fields.pdf", "Avalon Princeton - Preliminary Application Rev-Mar-2016-Fields.pdf"]},
{"type":"text", "label":"", "value":"extraIncomeSource3", "requiredBy":["Application-GF-Fields.pdf", "AffordableHousing_Application sales-Fields.pdf", "Avalon Princeton - Preliminary Application Rev-Mar-2016-Fields.pdf"]},
{"type":"text", "label":"", "value":"extraIncomeSource4", "requiredBy":["Application-GF-Fields.pdf", "Avalon Princeton - Preliminary Application Rev-Mar-2016-Fields.pdf"]},
{"type":"text", "label":"", "value":"hasAsianPacificEthnicity", "requiredBy":["Application-GF-Fields.pdf", "Application-PCV-Fields.pdf", "Avalon Princeton - Preliminary Application Rev-Mar-2016-Fields.pdf"]},
{"type":"text", "label":"", "value":"hasBlackEthnicity", "requiredBy":["Application-GF-Fields.pdf", "Application-PCV-Fields.pdf", "Avalon Princeton - Preliminary Application Rev-Mar-2016-Fields.pdf"]},
{"type":"text", "label":"", "value":"hasBothPreference", "requiredBy":["Application-GF-Fields.pdf"]},
{"type":"text", "label":"", "value":"hasBuyPreference", "requiredBy":["Application-GF-Fields.pdf"]},
{"type":"text", "label":"", "value":"hasHispanicEthnicity", "requiredBy":["Application-GF-Fields.pdf"]},
{"type":"text", "label":"", "value":"hasIndianAsianEthnicity", "requiredBy":["Application-GF-Fields.pdf", "Application-PCV-Fields.pdf", "Avalon Princeton - Preliminary Application Rev-Mar-2016-Fields.pdf"]},
{"type":"text", "label":"", "value":"hasIslanderEthnicity", "requiredBy":["Application-GF-Fields.pdf", "Application-PCV-Fields.pdf", "Avalon Princeton - Preliminary Application Rev-Mar-2016-Fields.pdf"]},
{"type":"text", "label":"", "value":"hasNonHispanicEthnicity", "requiredBy":["Application-GF-Fields.pdf"]},
{"type":"text", "label":"", "value":"hasntSexOffense", "requiredBy":["Application-GF-Fields.pdf"]},
{"type":"text", "label":"", "value":"hasntSpecialNeeds", "requiredBy":["Application-GF-Fields.pdf"]},
{"type":"text", "label":"", "value":"hasOtherEthnicity", "requiredBy":["Application-GF-Fields.pdf"]},
{"type":"text", "label":"", "value":"hasRentPreference", "requiredBy":["Application-GF-Fields.pdf"]},
{"type":"text", "label":"", "value":"hasSexOffense", "requiredBy":["Application-GF-Fields.pdf"]},
{"type":"text", "label":"", "value":"hasSpecialNeeds", "requiredBy":["Application-GF-Fields.pdf"]},
{"type":"text", "label":"", "value":"hasWhiteEthnicity", "requiredBy":["Application-GF-Fields.pdf", "Application-PCV-Fields.pdf", "Avalon Princeton - Preliminary Application Rev-Mar-2016-Fields.pdf"]},
{"type":"text", "label":"", "value":"home", "requiredBy":["Application-GF-Fields.pdf"]},
{"type":"text", "label":"", "value":"isHispanic", "requiredBy":["Application-PCV-Fields.pdf", "Avalon Princeton - Preliminary Application Rev-Mar-2016-Fields.pdf"]},
{"type":"text", "label":"", "value":"isNonHispanic", "requiredBy":["Application-PCV-Fields.pdf", "Avalon Princeton - Preliminary Application Rev-Mar-2016-Fields.pdf"]},
{"type":"text", "label":"", "value":"lastPaymentDate1", "requiredBy":["AffordableHousing_Application sales-Fields.pdf"]},
{"type":"text", "label":"", "value":"lastPaymentDate2", "requiredBy":["AffordableHousing_Application sales-Fields.pdf"]},
{"type":"text", "label":"", "value":"lastPaymentDate3", "requiredBy":["AffordableHousing_Application sales-Fields.pdf"]},
{"type":"text", "label":"", "value":"lastPaymentDate4", "requiredBy":["AffordableHousing_Application sales-Fields.pdf"]},
{"type":"text", "label":"", "value":"lenderName1", "requiredBy":["AffordableHousing_Application sales-Fields.pdf"]},
{"type":"text", "label":"", "value":"lenderName2", "requiredBy":["AffordableHousing_Application sales-Fields.pdf"]},
{"type":"text", "label":"", "value":"lenderName3", "requiredBy":["AffordableHousing_Application sales-Fields.pdf"]},
{"type":"text", "label":"", "value":"lenderName4", "requiredBy":["AffordableHousing_Application sales-Fields.pdf"]},
{"type":"text", "label":"", "value":"loanBalance1", "requiredBy":["AffordableHousing_Application sales-Fields.pdf"]},
{"type":"text", "label":"", "value":"loanBalance2", "requiredBy":["AffordableHousing_Application sales-Fields.pdf"]},
{"type":"text", "label":"", "value":"loanBalance3", "requiredBy":["AffordableHousing_Application sales-Fields.pdf"]},
{"type":"text", "label":"", "value":"loanBalance4", "requiredBy":["AffordableHousing_Application sales-Fields.pdf"]},
{"type":"text", "label":"", "value":"loanType1", "requiredBy":["AffordableHousing_Application sales-Fields.pdf"]},
{"type":"text", "label":"", "value":"loanType2", "requiredBy":["AffordableHousing_Application sales-Fields.pdf"]},
{"type":"text", "label":"", "value":"loanType3", "requiredBy":["AffordableHousing_Application sales-Fields.pdf"]},
{"type":"text", "label":"", "value":"member1", "requiredBy":["Application-GF-Fields.pdf", "AffordableHousing_Application sales-Fields.pdf", "Application-PCV-Fields.pdf", "Avalon Princeton - Preliminary Application Rev-Mar-2016-Fields.pdf"]},
{"type":"text", "label":"", "value":"member2", "requiredBy":["Application-GF-Fields.pdf", "AffordableHousing_Application sales-Fields.pdf", "Application-PCV-Fields.pdf", "Avalon Princeton - Preliminary Application Rev-Mar-2016-Fields.pdf"]},
{"type":"text", "label":"", "value":"member3", "requiredBy":["Application-GF-Fields.pdf", "AffordableHousing_Application sales-Fields.pdf", "Application-PCV-Fields.pdf", "Avalon Princeton - Preliminary Application Rev-Mar-2016-Fields.pdf"]},
{"type":"text", "label":"", "value":"member4", "requiredBy":["Application-GF-Fields.pdf", "AffordableHousing_Application sales-Fields.pdf", "Application-PCV-Fields.pdf", "Avalon Princeton - Preliminary Application Rev-Mar-2016-Fields.pdf"]},
{"type":"text", "label":"", "value":"member5", "requiredBy":["Application-GF-Fields.pdf", "AffordableHousing_Application sales-Fields.pdf", "Application-PCV-Fields.pdf", "Avalon Princeton - Preliminary Application Rev-Mar-2016-Fields.pdf"]},
{"type":"text", "label":"", "value":"member6", "requiredBy":["Application-GF-Fields.pdf", "Application-PCV-Fields.pdf", "Avalon Princeton - Preliminary Application Rev-Mar-2016-Fields.pdf"]},
{"type":"text", "label":"", "value":"memberDOB1", "requiredBy":["AffordableHousing_Application sales-Fields.pdf", "Application-PCV-Fields.pdf", "Avalon Princeton - Preliminary Application Rev-Mar-2016-Fields.pdf"]},
{"type":"text", "label":"", "value":"memberDOB2", "requiredBy":["AffordableHousing_Application sales-Fields.pdf", "Application-PCV-Fields.pdf", "Avalon Princeton - Preliminary Application Rev-Mar-2016-Fields.pdf"]},
{"type":"text", "label":"", "value":"memberDOB3", "requiredBy":["AffordableHousing_Application sales-Fields.pdf", "Application-PCV-Fields.pdf", "Avalon Princeton - Preliminary Application Rev-Mar-2016-Fields.pdf"]},
{"type":"text", "label":"", "value":"memberDOB4", "requiredBy":["AffordableHousing_Application sales-Fields.pdf", "Application-PCV-Fields.pdf", "Avalon Princeton - Preliminary Application Rev-Mar-2016-Fields.pdf"]},
{"type":"text", "label":"", "value":"memberDOB5", "requiredBy":["AffordableHousing_Application sales-Fields.pdf", "Application-PCV-Fields.pdf", "Avalon Princeton - Preliminary Application Rev-Mar-2016-Fields.pdf"]},
{"type":"text", "label":"", "value":"memberDOB6", "requiredBy":["Application-PCV-Fields.pdf", "Avalon Princeton - Preliminary Application Rev-Mar-2016-Fields.pdf"]},
{"type":"text", "label":"", "value":"memberEmployer1", "requiredBy":["AffordableHousing_Application sales-Fields.pdf", "Application-PCV-Fields.pdf", "Avalon Princeton - Preliminary Application Rev-Mar-2016-Fields.pdf"]},
{"type":"text", "label":"", "value":"memberEmployer2", "requiredBy":["AffordableHousing_Application sales-Fields.pdf", "Application-PCV-Fields.pdf", "Avalon Princeton - Preliminary Application Rev-Mar-2016-Fields.pdf"]},
{"type":"text", "label":"", "value":"memberEmployer3", "requiredBy":["AffordableHousing_Application sales-Fields.pdf", "Application-PCV-Fields.pdf", "Avalon Princeton - Preliminary Application Rev-Mar-2016-Fields.pdf"]},
{"type":"text", "label":"", "value":"memberEmployer4", "requiredBy":["AffordableHousing_Application sales-Fields.pdf", "Application-PCV-Fields.pdf", "Avalon Princeton - Preliminary Application Rev-Mar-2016-Fields.pdf"]},
{"type":"text", "label":"", "value":"memberEmployer5", "requiredBy":["AffordableHousing_Application sales-Fields.pdf", "Application-PCV-Fields.pdf", "Avalon Princeton - Preliminary Application Rev-Mar-2016-Fields.pdf"]},
{"type":"text", "label":"", "value":"memberEmploymentDuration1", "requiredBy":["AffordableHousing_Application sales-Fields.pdf", "Application-PCV-Fields.pdf", "Avalon Princeton - Preliminary Application Rev-Mar-2016-Fields.pdf"]},
{"type":"text", "label":"", "value":"memberEmploymentDuration2", "requiredBy":["AffordableHousing_Application sales-Fields.pdf", "Application-PCV-Fields.pdf", "Avalon Princeton - Preliminary Application Rev-Mar-2016-Fields.pdf"]},
{"type":"text", "label":"", "value":"memberEmploymentDuration3", "requiredBy":["AffordableHousing_Application sales-Fields.pdf", "Application-PCV-Fields.pdf", "Avalon Princeton - Preliminary Application Rev-Mar-2016-Fields.pdf"]},
{"type":"text", "label":"", "value":"memberEmploymentDuration4", "requiredBy":["AffordableHousing_Application sales-Fields.pdf", "Application-PCV-Fields.pdf", "Avalon Princeton - Preliminary Application Rev-Mar-2016-Fields.pdf"]},
{"type":"text", "label":"", "value":"memberEmploymentDuration5", "requiredBy":["AffordableHousing_Application sales-Fields.pdf", "Application-PCV-Fields.pdf", "Avalon Princeton - Preliminary Application Rev-Mar-2016-Fields.pdf"]},
{"type":"text", "label":"", "value":"memberGrossAnnualIncome1", "requiredBy":["Application-GF-Fields.pdf", "AffordableHousing_Application sales-Fields.pdf", "Application-PCV-Fields.pdf", "Avalon Princeton - Preliminary Application Rev-Mar-2016-Fields.pdf"]},
{"type":"text", "label":"", "value":"memberGrossAnnualIncome2", "requiredBy":["Application-GF-Fields.pdf", "AffordableHousing_Application sales-Fields.pdf", "Application-PCV-Fields.pdf", "Avalon Princeton - Preliminary Application Rev-Mar-2016-Fields.pdf"]},
{"type":"text", "label":"", "value":"memberGrossAnnualIncome3", "requiredBy":["Application-GF-Fields.pdf", "AffordableHousing_Application sales-Fields.pdf", "Application-PCV-Fields.pdf", "Avalon Princeton - Preliminary Application Rev-Mar-2016-Fields.pdf"]},
{"type":"text", "label":"", "value":"memberGrossAnnualIncome4", "requiredBy":["Application-GF-Fields.pdf", "AffordableHousing_Application sales-Fields.pdf", "Application-PCV-Fields.pdf", "Avalon Princeton - Preliminary Application Rev-Mar-2016-Fields.pdf"]},
{"type":"text", "label":"", "value":"memberGrossAnnualIncome5", "requiredBy":["Application-GF-Fields.pdf", "AffordableHousing_Application sales-Fields.pdf", "Application-PCV-Fields.pdf", "Avalon Princeton - Preliminary Application Rev-Mar-2016-Fields.pdf"]},
{"type":"text", "label":"", "value":"memberName1", "requiredBy":["AffordableHousing_Application sales-Fields.pdf", "Application-PCV-Fields.pdf", "Avalon Princeton - Preliminary Application Rev-Mar-2016-Fields.pdf"]},
{"type":"text", "label":"", "value":"memberName2", "requiredBy":["AffordableHousing_Application sales-Fields.pdf", "Application-PCV-Fields.pdf", "Avalon Princeton - Preliminary Application Rev-Mar-2016-Fields.pdf"]},
{"type":"text", "label":"", "value":"memberName3", "requiredBy":["AffordableHousing_Application sales-Fields.pdf", "Application-PCV-Fields.pdf", "Avalon Princeton - Preliminary Application Rev-Mar-2016-Fields.pdf"]},
{"type":"text", "label":"", "value":"memberName4", "requiredBy":["AffordableHousing_Application sales-Fields.pdf", "Application-PCV-Fields.pdf", "Avalon Princeton - Preliminary Application Rev-Mar-2016-Fields.pdf"]},
{"type":"text", "label":"", "value":"memberName5", "requiredBy":["AffordableHousing_Application sales-Fields.pdf", "Application-PCV-Fields.pdf", "Avalon Princeton - Preliminary Application Rev-Mar-2016-Fields.pdf"]},
{"type":"text", "label":"", "value":"memberRelationship1", "requiredBy":["AffordableHousing_Application sales-Fields.pdf", "Application-PCV-Fields.pdf", "Avalon Princeton - Preliminary Application Rev-Mar-2016-Fields.pdf"]},
{"type":"text", "label":"", "value":"memberRelationship2", "requiredBy":["AffordableHousing_Application sales-Fields.pdf", "Application-PCV-Fields.pdf", "Avalon Princeton - Preliminary Application Rev-Mar-2016-Fields.pdf"]},
{"type":"text", "label":"", "value":"memberRelationship3", "requiredBy":["AffordableHousing_Application sales-Fields.pdf", "Application-PCV-Fields.pdf", "Avalon Princeton - Preliminary Application Rev-Mar-2016-Fields.pdf"]},
{"type":"text", "label":"", "value":"memberRelationship4", "requiredBy":["AffordableHousing_Application sales-Fields.pdf", "Application-PCV-Fields.pdf", "Avalon Princeton - Preliminary Application Rev-Mar-2016-Fields.pdf"]},
{"type":"text", "label":"", "value":"memberRelationship5", "requiredBy":["AffordableHousing_Application sales-Fields.pdf", "Application-PCV-Fields.pdf", "Avalon Princeton - Preliminary Application Rev-Mar-2016-Fields.pdf"]},
{"type":"text", "label":"", "value":"memberRelationship6", "requiredBy":["Application-PCV-Fields.pdf", "Avalon Princeton - Preliminary Application Rev-Mar-2016-Fields.pdf"]},
{"type":"text", "label":"", "value":"memberSex1", "requiredBy":["AffordableHousing_Application sales-Fields.pdf", "Application-PCV-Fields.pdf", "Avalon Princeton - Preliminary Application Rev-Mar-2016-Fields.pdf"]},
{"type":"text", "label":"", "value":"memberSex2", "requiredBy":["AffordableHousing_Application sales-Fields.pdf", "Application-PCV-Fields.pdf", "Avalon Princeton - Preliminary Application Rev-Mar-2016-Fields.pdf"]},
{"type":"text", "label":"", "value":"memberSex3", "requiredBy":["AffordableHousing_Application sales-Fields.pdf", "Application-PCV-Fields.pdf", "Avalon Princeton - Preliminary Application Rev-Mar-2016-Fields.pdf"]},
{"type":"text", "label":"", "value":"memberSex4", "requiredBy":["AffordableHousing_Application sales-Fields.pdf", "Application-PCV-Fields.pdf", "Avalon Princeton - Preliminary Application Rev-Mar-2016-Fields.pdf"]},
{"type":"text", "label":"", "value":"memberSex5", "requiredBy":["AffordableHousing_Application sales-Fields.pdf", "Application-PCV-Fields.pdf", "Avalon Princeton - Preliminary Application Rev-Mar-2016-Fields.pdf"]},
{"type":"text", "label":"", "value":"memberSex6", "requiredBy":["Application-PCV-Fields.pdf", "Avalon Princeton - Preliminary Application Rev-Mar-2016-Fields.pdf"]},
{"type":"text", "label":"", "value":"memberSSN1", "requiredBy":["AffordableHousing_Application sales-Fields.pdf", "Application-PCV-Fields.pdf", "Avalon Princeton - Preliminary Application Rev-Mar-2016-Fields.pdf"]},
{"type":"text", "label":"", "value":"memberSSN2", "requiredBy":["AffordableHousing_Application sales-Fields.pdf", "Application-PCV-Fields.pdf", "Avalon Princeton - Preliminary Application Rev-Mar-2016-Fields.pdf"]},
{"type":"text", "label":"", "value":"memberSSN3", "requiredBy":["AffordableHousing_Application sales-Fields.pdf", "Application-PCV-Fields.pdf", "Avalon Princeton - Preliminary Application Rev-Mar-2016-Fields.pdf"]},
{"type":"text", "label":"", "value":"memberSSN4", "requiredBy":["AffordableHousing_Application sales-Fields.pdf", "Application-PCV-Fields.pdf", "Avalon Princeton - Preliminary Application Rev-Mar-2016-Fields.pdf"]},
{"type":"text", "label":"", "value":"memberSSN5", "requiredBy":["AffordableHousing_Application sales-Fields.pdf", "Application-PCV-Fields.pdf", "Avalon Princeton - Preliminary Application Rev-Mar-2016-Fields.pdf"]},
{"type":"text", "label":"", "value":"memberSSN6", "requiredBy":["Application-PCV-Fields.pdf", "Avalon Princeton - Preliminary Application Rev-Mar-2016-Fields.pdf"]},
{"type":"text", "label":"", "value":"name", "requiredBy":["Application-GF-Fields.pdf", "AffordableHousing_Application sales-Fields.pdf", "Application-PCV-Fields.pdf", "Avalon Princeton - Preliminary Application Rev-Mar-2016-Fields.pdf"]},
{"type":"text", "label":"", "value":"phone", "requiredBy":["AffordableHousing_Application sales-Fields.pdf", "Application-PCV-Fields.pdf", "Avalon Princeton - Preliminary Application Rev-Mar-2016-Fields.pdf"]},
{"type":"text", "label":"", "value":"sexOffenseDate", "requiredBy":["Application-GF-Fields.pdf"]},
{"type":"text", "label":"", "value":"sexOffenseName", "requiredBy":["Application-GF-Fields.pdf"]},
{"type":"text", "label":"", "value":"sexOffenseState", "requiredBy":["Application-GF-Fields.pdf"]},
{"type":"text", "label":"", "value":"specialNeedsDescription", "requiredBy":["Application-GF-Fields.pdf"]},
{"type":"text", "label":"", "value":"state", "requiredBy":["Application-GF-Fields.pdf", "AffordableHousing_Application sales-Fields.pdf", "Application-PCV-Fields.pdf", "Avalon Princeton - Preliminary Application Rev-Mar-2016-Fields.pdf"]},
{"type":"text", "label":"", "value":"totalHouseholdAnnualIncome", "requiredBy":["Application-GF-Fields.pdf", "AffordableHousing_Application sales-Fields.pdf", "Application-PCV-Fields.pdf", "Avalon Princeton - Preliminary Application Rev-Mar-2016-Fields.pdf"]},
{"type":"text", "label":"", "value":"willJoinHabitat", "requiredBy":["Application-GF-Fields.pdf"]},
{"type":"text", "label":"", "value":"work", "requiredBy":["Application-GF-Fields.pdf", "AffordableHousing_Application sales-Fields.pdf", "Application-PCV-Fields.pdf", "Avalon Princeton - Preliminary Application Rev-Mar-2016-Fields.pdf"]},
{"type":"text", "label":"", "value":"zip", "requiredBy":["Application-GF-Fields.pdf", "AffordableHousing_Application sales-Fields.pdf", "Application-PCV-Fields.pdf", "Avalon Princeton - Preliminary Application Rev-Mar-2016-Fields.pdf"]},
{"type":"text", "label":"", "value":"asset1", "requiredBy":["Application-PCV-Fields.pdf"]},
{"type":"text", "label":"", "value":"accountType1", "requiredBy":["Application-PCV-Fields.pdf"]},
{"type":"text", "label":"", "value":"asset2", "requiredBy":["Application-PCV-Fields.pdf"]},
{"type":"text", "label":"", "value":"accountType2", "requiredBy":["Application-PCV-Fields.pdf"]},
{"type":"text", "label":"", "value":"asset3", "requiredBy":["Application-PCV-Fields.pdf"]},
{"type":"text", "label":"", "value":"accountType3", "requiredBy":["Application-PCV-Fields.pdf"]},
{"type":"text", "label":"", "value":"asset4", "requiredBy":["Application-PCV-Fields.pdf"]},
{"type":"text", "label":"", "value":"accountType4", "requiredBy":["Application-PCV-Fields.pdf"]},
{"type":"text", "label":"", "value":"supplementalIncomeAmount1", "requiredBy":["Application-PCV-Fields.pdf"]},
{"type":"text", "label":"", "value":"supplementalIncomeFrequency1", "requiredBy":["Application-PCV-Fields.pdf"]},
{"type":"text", "label":"", "value":"supplementalIncomeSource1", "requiredBy":["Application-PCV-Fields.pdf"]},
{"type":"text", "label":"", "value":"supplementalIncomeAmount2", "requiredBy":["Application-PCV-Fields.pdf"]},
{"type":"text", "label":"", "value":"supplementalIncomeFrequency2", "requiredBy":["Application-PCV-Fields.pdf"]},
{"type":"text", "label":"", "value":"supplementalIncomeSource2", "requiredBy":["Application-PCV-Fields.pdf"]},
{"type":"text", "label":"", "value":"supplementalIncomeAmount3", "requiredBy":["Application-PCV-Fields.pdf"]},
{"type":"text", "label":"", "value":"supplementalIncomeFrequency3", "requiredBy":["Application-PCV-Fields.pdf"]},
{"type":"text", "label":"", "value":"supplementalIncomeSource3", "requiredBy":["Application-PCV-Fields.pdf"]},
{"type":"text", "label":"", "value":"supplementalIncomeAmount4", "requiredBy":["Application-PCV-Fields.pdf"]},
{"type":"text", "label":"", "value":"supplementalIncomeFrequency4", "requiredBy":["Application-PCV-Fields.pdf"]},
{"type":"text", "label":"", "value":"supplementalIncomeSource4", "requiredBy":["Application-PCV-Fields.pdf"]},
{"type":"text", "label":"", "value":"applicantDate", "requiredBy":["Application-PCV-Fields.pdf"]},
{"type":"text", "label":"", "value":"coApplicantDate1", "requiredBy":["Application-PCV-Fields.pdf"]},
{"type":"text", "label":"", "value":"coApplicantDate2", "requiredBy":["Application-PCV-Fields.pdf"]}
]